<?xml version="1.0" encoding="UTF-8"?>
<Entities
 build="b140"
 majorVersion="8"
 minorVersion="2"
 modelPersistenceProviderPackage="PostgresPersistenceProviderPackage"
 revision="1"
 schemaVersion="1020"
 universal="">
    <Things>
        <Thing
         description=""
         documentationContent=""
         effectiveThingPackage="IndustrialGateway"
         enabled="true"
         homeMashup=""
         identifier=""
         lastModifiedDate="2018-05-24T17:48:57.173Z"
         name="BayerIndustrialConnectionServer"
         projectName="BayerIoT"
         published="false"
         tags=""
         thingTemplate="IndustrialGateway"
         valueStream="">
            <avatar></avatar>
            <DesignTimePermissions>
                <Create></Create>
                <Read></Read>
                <Update></Update>
                <Delete></Delete>
                <Metadata></Metadata>
            </DesignTimePermissions>
            <RunTimePermissions></RunTimePermissions>
            <VisibilityPermissions>
                <Visibility></Visibility>
            </VisibilityPermissions>
            <ConfigurationTables></ConfigurationTables>
            <ThingShape>
                <PropertyDefinitions></PropertyDefinitions>
                <ServiceDefinitions></ServiceDefinitions>
                <EventDefinitions></EventDefinitions>
                <ServiceMappings></ServiceMappings>
                <ServiceImplementations></ServiceImplementations>
                <Subscriptions></Subscriptions>
            </ThingShape>
            <PropertyBindings></PropertyBindings>
            <RemotePropertyBindings></RemotePropertyBindings>
            <RemoteServiceBindings></RemoteServiceBindings>
            <RemoteEventBindings></RemoteEventBindings>
            <AlertConfigurations></AlertConfigurations>
            <ImplementedShapes></ImplementedShapes>
            <ThingProperties>
                <FullProjectName>
                    <Value>
                    <![CDATA[
                    C:\ProgramData\Kepware\KEPServerEX\V6\default.opf
                    ]]>
                    </Value>
                    <Timestamp>2018-06-08T14:09:11.275Z</Timestamp>
                    <Quality>GOOD</Quality>
                </FullProjectName>
                <ProductName>
                    <Value>
                    <![CDATA[
                    KEPServerEX
                    ]]>
                    </Value>
                    <Timestamp>2018-06-08T14:09:11.275Z</Timestamp>
                    <Quality>GOOD</Quality>
                </ProductName>
                <ProjectName>
                    <Value>
                    <![CDATA[
                    default.opf
                    ]]>
                    </Value>
                    <Timestamp>2018-06-08T14:09:11.275Z</Timestamp>
                    <Quality>GOOD</Quality>
                </ProjectName>
                <ClientCount>
                    <Value>0</Value>
                    <Timestamp>2018-06-08T14:09:11.275Z</Timestamp>
                    <Quality>GOOD</Quality>
                </ClientCount>
                <TotalTagCount>
                    <Value>14</Value>
                    <Timestamp>2018-06-08T14:09:42.927Z</Timestamp>
                    <Quality>GOOD</Quality>
                </TotalTagCount>
                <DroppedUpdates>
                    <Value>0</Value>
                    <Timestamp>2018-06-08T14:09:11.275Z</Timestamp>
                    <Quality>GOOD</Quality>
                </DroppedUpdates>
                <Hostname>
                    <Value>
                    <![CDATA[
                    WIN-RF4VEUNUC3P
                    ]]>
                    </Value>
                    <Timestamp>2018-06-08T14:09:11.275Z</Timestamp>
                    <Quality>GOOD</Quality>
                </Hostname>
                <IndustrialThingCount>
                    <Value>1</Value>
                    <Timestamp>2018-06-08T14:09:42.927Z</Timestamp>
                    <Quality>GOOD</Quality>
                </IndustrialThingCount>
                <PropertyCount>
                    <Value>1</Value>
                    <Timestamp>2018-06-08T14:09:42.927Z</Timestamp>
                    <Quality>GOOD</Quality>
                </PropertyCount>
                <ProductVersion>
                    <Value>
                    <![CDATA[
                    6.4
                    ]]>
                    </Value>
                    <Timestamp>2018-06-08T14:09:11.275Z</Timestamp>
                    <Quality>GOOD</Quality>
                </ProductVersion>
                <UpdatesPerSecond>
                    <Value>1.9</Value>
                    <Timestamp>2018-06-08T14:09:53.191Z</Timestamp>
                    <Quality>GOOD</Quality>
                </UpdatesPerSecond>
                <DateTime>
                    <Value>2018-06-08T14:11:33.124Z</Value>
                    <Timestamp>2018-06-08T14:11:33.982Z</Timestamp>
                    <Quality>GOOD</Quality>
                </DateTime>
                <LicensedFeatures>
                    <Value>
                        <infoTable>
                            <DataShape>
                                <FieldDefinitions>
                                    <FieldDefinition
                                     baseType="STRING"
                                     description=""
                                     name="element"
                                     ordinal="0"></FieldDefinition>
                                </FieldDefinitions>
                            </DataShape>
                            <Rows></Rows>
                        </infoTable>
                    </Value>
                    <Timestamp>2018-06-08T14:11:33.982Z</Timestamp>
                    <Quality>GOOD</Quality>
                </LicensedFeatures>
                <ActiveTagCount>
                    <Value>14</Value>
                    <Timestamp>2018-06-08T14:09:42.927Z</Timestamp>
                    <Quality>GOOD</Quality>
                </ActiveTagCount>
                <ProjectTitle>
                    <Value>
                    <![CDATA[
                    Simulation Driver Demo
                    ]]>
                    </Value>
                    <Timestamp>2018-06-08T14:09:11.275Z</Timestamp>
                    <Quality>GOOD</Quality>
                </ProjectTitle>
                <OpcClientNames>
                    <Value>
                        <infoTable>
                            <DataShape>
                                <FieldDefinitions>
                                    <FieldDefinition
                                     baseType="STRING"
                                     description=""
                                     name="element"
                                     ordinal="0"></FieldDefinition>
                                </FieldDefinitions>
                            </DataShape>
                            <Rows>
                                <Row>
                                    <element></element>
                                </Row>
                            </Rows>
                        </infoTable>
                    </Value>
                    <Timestamp>2018-06-08T14:11:33.982Z</Timestamp>
                    <Quality>GOOD</Quality>
                </OpcClientNames>
                <TimeLimitedFeatures>
                    <Value>
                        <infoTable>
                            <DataShape>
                                <FieldDefinitions>
                                    <FieldDefinition
                                     baseType="STRING"
                                     description=""
                                     name="element"
                                     ordinal="0"></FieldDefinition>
                                </FieldDefinitions>
                            </DataShape>
                            <Rows></Rows>
                        </infoTable>
                    </Value>
                    <Timestamp>2018-06-08T14:11:33.982Z</Timestamp>
                    <Quality>GOOD</Quality>
                </TimeLimitedFeatures>
                <ExpiredFeatures>
                    <Value>
                        <infoTable>
                            <DataShape>
                                <FieldDefinitions>
                                    <FieldDefinition
                                     baseType="STRING"
                                     description=""
                                     name="element"
                                     ordinal="0"></FieldDefinition>
                                </FieldDefinitions>
                            </DataShape>
                            <Rows></Rows>
                        </infoTable>
                    </Value>
                    <Timestamp>2018-06-08T14:11:33.982Z</Timestamp>
                    <Quality>GOOD</Quality>
                </ExpiredFeatures>
                <IndustrialFileRepository>
                    <Value>
                    <![CDATA[
                    SystemRepository
                    ]]>
                    </Value>
                    <Timestamp>2018-06-08T14:09:37.826Z</Timestamp>
                    <Quality>GOOD</Quality>
                </IndustrialFileRepository>
                <lastConnection>
                    <Value>2018-06-08T14:09:38.808Z</Value>
                    <Timestamp>2018-06-08T14:09:38.808Z</Timestamp>
                    <Quality>GOOD</Quality>
                </lastConnection>
            </ThingProperties>
        </Thing>
    </Things>
</Entities>
